funcverbnet/__init__.py
funcverbnet/cli.py
funcverbnet/funcverbnet.py
funcverbnet/model.py
funcverbnet/sentence_classifier.py
funcverbnet/test.py
funcverbnet/data/Annotated_data.csv
funcverbnet/data/add_train_data.csv
funcverbnet/data/f_pattern.json
funcverbnet/data/f_verb.json
funcverbnet/data/final_train_data.csv
funcverbnet/data/functionality_category.json
funcverbnet/data/phrase_pattern.json
funcverbnet/data/semantic_role.json
funcverbnet/data/sentences_with_annotation.csv
funcverbnet/data/test_data.csv
funcverbnet/data/train.csv
funcverbnet/data/update_train_data.csv
funcverbnet/data/verb.json
funcverbnet/model/sentence_classification.model
funcverbnet-0.2.2.dist-info/AUTHORS.rst
funcverbnet-0.2.2.dist-info/LICENSE
funcverbnet-0.2.2.dist-info/METADATA
funcverbnet-0.2.2.dist-info/WHEEL
funcverbnet-0.2.2.dist-info/entry_points.txt
funcverbnet-0.2.2.dist-info/top_level.txt
funcverbnet-0.2.2.dist-info/RECORD
