Metadata-Version: 2.1
Name: funcverbnet
Version: 0.2.2
Summary: Provides a knowledge system constructed from functionality categories, verbs, and phrase patterns, as well as functionality for fine-grained analysis of functionality descriptions based on this knowledge system
Home-page: https://github.com/FudanSELab/funcverbnet
Author: Software Engineering Laboratory of Fudan University
Author-email: lmwtclmwtc@outlook.com
License: BSD license
Keywords: funcverbnet
Platform: UNKNOWN
Classifier: Development Status :: 2 - Pre-Alpha
Classifier: Intended Audience :: Developers
Classifier: License :: OSI Approved :: BSD License
Classifier: Natural Language :: English
Classifier: Programming Language :: Python :: 3
Classifier: Programming Language :: Python :: 3.6
Classifier: Programming Language :: Python :: 3.7
Classifier: Programming Language :: Python :: 3.8
Requires-Python: >=3.6
Requires-Dist: Click (>=7.0)
Requires-Dist: pandas
Requires-Dist: fasttext (~=0.9.2)
